ossbomer/__init__.py
ossbomer/cli.py
ossbomer/dataset_manager.py
ossbomer/license_validator.py
ossbomer/metadata_validator.py
ossbomer/purl_validator.py
ossbomer/sbom_parser.py
ossbomer/validation_report.py
ossbomer/datasets/cyclonedx_schema.json
ossbomer/datasets/license_rules.json
ossbomer/datasets/spdx_schema.json
ossbomer/datasets/package_signatures/example-package.json
ossbomer/datasets/package_signatures/index.json
ossbomer/datasets/package_signatures/insecure-package.json
ossbomer-0.1.4.dist-info/LICENSE
ossbomer-0.1.4.dist-info/METADATA
ossbomer-0.1.4.dist-info/WHEEL
ossbomer-0.1.4.dist-info/entry_points.txt
ossbomer-0.1.4.dist-info/top_level.txt
ossbomer-0.1.4.dist-info/RECORD
